<?xml version="1.0" encoding="UTF-8"?>
<STEP-ProductInformation ContextID="Context1" WorkspaceID="Main" UseContextLocale="false">
    <Qualifiers>
        <Qualifier ID="en-US">
            <DimensionPointLink DimensionPointID="en-US"></DimensionPointLink>
        </Qualifier>
    </Qualifiers>
    <AttributeList>
        <Attribute ID="4bc2ed06-8fab-455c-b5d5-1b18c3558e03" MultiValued="false" ProductMode="Normal" FullTextIndexed="false" ExternallyMaintained="true" Derived="false" HierarchicalFiltering="false" ClassificationHierarchicalFiltering="false" Mandatory="false">
            <Name QualifierID="en-US">Number of Tons</Name>
            <ListOfValueLink ListOfValueID="6d062105-b913-4f90-9862-d0c7670b2440"></ListOfValueLink>
            <AttributeGroupLink AttributeGroupID="Category Specific"></AttributeGroupLink>
            <UserTypeLink UserTypeID="Branch"></UserTypeLink>
            <UserTypeLink UserTypeID="Family"></UserTypeLink>
            <UserTypeLink UserTypeID="Item"></UserTypeLink>
            <UserTypeLink UserTypeID="Leaf"></UserTypeLink>
            <UserTypeLink UserTypeID="Variant"></UserTypeLink>
        </Attribute>
    </AttributeList>
</STEP-ProductInformation>