<?xml version="1.0" encoding="UTF-8"?>
<STEP-ProductInformation ContextID="Context1" WorkspaceID="Main" UseContextLocale="false">
    <AttributeGroupList>
        <AttributeGroup ID="EnrichHazmat" ShowInWorkbench="false" ManuallySorted="true" ParentID="EnrichRequiredAttributes">
            <Name QualifierID="Qualifier root">Enrich Hazmat Required Attributes</Name>
            <AttributeSequence>
                <AttributeLink AttributeID="4b429d41-65b3-479c-a8ee-35a49868d7c6"></AttributeLink>
                <AttributeLink AttributeID="87c1cda9-abdb-48a3-8f43-06fcb2c3562f"></AttributeLink>
                <AttributeLink AttributeID="d069f566-c68b-4216-937b-0b0d146e2a7a"></AttributeLink>
                <AttributeLink AttributeID="93e55aaa-0cce-47bf-a744-edea7e24e07f"></AttributeLink>
                <AttributeLink AttributeID="2d353851-b3ed-40cc-b238-a8cb9556ebee"></AttributeLink>
                <AttributeLink AttributeID="7c23cc82-8cc5-47f2-839f-ec99bed78a58"></AttributeLink>
                <AttributeLink AttributeID="001cb259-366e-4541-be2b-8e8b7c0d3dbd"></AttributeLink>
                <AttributeLink AttributeID="aae79405-1e48-4f96-8d17-c2fa2dedafa4"></AttributeLink>
            </AttributeSequence>
        </AttributeGroup>
    </AttributeGroupList>
</STEP-ProductInformation>